odoo/addons/l10n_ec_delivery_note/README.rst
odoo/addons/l10n_ec_delivery_note/__init__.py
odoo/addons/l10n_ec_delivery_note/__manifest__.py
odoo/addons/l10n_ec_delivery_note/data/email_template.xml
odoo/addons/l10n_ec_delivery_note/data/l10n_latam.document.type.csv
odoo/addons/l10n_ec_delivery_note/data/edi_templates/edi_delivery_note.xml
odoo/addons/l10n_ec_delivery_note/data/xsd/GuiaRemision_V1.0.0.xsd
odoo/addons/l10n_ec_delivery_note/data/xsd/GuiaRemision_V1.1.0.xsd
odoo/addons/l10n_ec_delivery_note/i18n/l10n_ec_delivery_note.pot
odoo/addons/l10n_ec_delivery_note/models/__init__.py
odoo/addons/l10n_ec_delivery_note/models/account_edi_document.py
odoo/addons/l10n_ec_delivery_note/models/account_edi_format.py
odoo/addons/l10n_ec_delivery_note/models/account_move.py
odoo/addons/l10n_ec_delivery_note/models/delivery_note.py
odoo/addons/l10n_ec_delivery_note/models/delivery_note_line.py
odoo/addons/l10n_ec_delivery_note/models/l10_latam_document_type.py
odoo/addons/l10n_ec_delivery_note/models/mail_template.py
odoo/addons/l10n_ec_delivery_note/models/res_company.py
odoo/addons/l10n_ec_delivery_note/models/res_config.py
odoo/addons/l10n_ec_delivery_note/models/res_partner.py
odoo/addons/l10n_ec_delivery_note/models/sale_order.py
odoo/addons/l10n_ec_delivery_note/models/stock_picking.py
odoo/addons/l10n_ec_delivery_note/models/stock_picking_type.py
odoo/addons/l10n_ec_delivery_note/report/report_delivery_note.xml
odoo/addons/l10n_ec_delivery_note/report/report_e_delivery_note.xml
odoo/addons/l10n_ec_delivery_note/security/ir.model.access.csv
odoo/addons/l10n_ec_delivery_note/security/security.xml
odoo/addons/l10n_ec_delivery_note/static/description/icon.png
odoo/addons/l10n_ec_delivery_note/tests/__init__.py
odoo/addons/l10n_ec_delivery_note/tests/test_l10n_ec_delivery_note_common.py
odoo/addons/l10n_ec_delivery_note/tests/test_l10n_ec_edi_delivery_note.py
odoo/addons/l10n_ec_delivery_note/tests/test_l10n_ec_mail.py
odoo_addon_l10n_ec_delivery_note-15.0.1.0.1.dist-info/METADATA
odoo_addon_l10n_ec_delivery_note-15.0.1.0.1.dist-info/WHEEL
odoo_addon_l10n_ec_delivery_note-15.0.1.0.1.dist-info/top_level.txt
odoo_addon_l10n_ec_delivery_note-15.0.1.0.1.dist-info/RECORD
